LICENSE
MANIFEST.in
README.md
REQUIREMENTS
setup.py
bin/flo
flo/__init__.py
flo/colors.py
flo/decorators.py
flo/exceptions.py
flo/logger.py
flo/notify.py
flo/parser.py
flo/shell.py
flo/types.py
flo.egg-info/PKG-INFO
flo.egg-info/SOURCES.txt
flo.egg-info/dependency_links.txt
flo.egg-info/not-zip-safe
flo.egg-info/requires.txt
flo.egg-info/top_level.txt
flo/commands/__init__.py
flo/commands/archive.py
flo/commands/base.py
flo/commands/clean.py
flo/commands/run.py
flo/commands/status.py
flo/resources/__init__.py
flo/resources/base.py
flo/resources/file_system.py
flo/tasks/__init__.py
flo/tasks/graph.py
flo/tasks/task.py
flo/templates/__init__.py