Metadata-Version: 1.1
Name: flo
Version: 1.0.0
Summary: enable rapid iteration and development of data workflows
Home-page: https://github.com/deanmalmgren/flo
Author: Dean Malmgren
Author-email: dean.malmgren@datascopeanalytics.com
License: MIT
Download-URL: https://github.com/deanmalmgren/flo/archives/master
Platform: UNKNOWN
